{"type":"info","show":{"tags":true,"location":false,"time":true,"date":false},"context":{"tags":[{"msg":"Express","colors":"cyan"},{"msg":"::1","colors":"red"},{"msg":"POST","colors":"green"},{"msg":"DESKTOP","colors":"grey"}],"file":false,"time":1514528917414,"location":{"filename":"expressLogger.js","line":43}},"args":{"0":"/api/user/login"},"contextString":"\u001b[36m[Express]\u001b[39m\u001b[31m[::1]\u001b[39m\u001b[32m[POST]\u001b[39m\u001b[90m[DESKTOP]\u001b[39m 2017-12-29T06:28:37.414Z ","argsString":"/api/user/login","message":"\u001b[36m[Express]\u001b[39m\u001b[31m[::1]\u001b[39m\u001b[32m[POST]\u001b[39m\u001b[90m[DESKTOP]\u001b[39m 2017-12-29T06:28:37.414Z /api/user/login"}
{"type":"info","show":{"tags":true,"location":false,"time":true,"date":false},"context":{"tags":[{"msg":"Express","colors":"cyan"},{"msg":"::1","colors":"red"},{"msg":"POST","colors":"green"},{"msg":"DESKTOP","colors":"grey"}],"file":false,"time":1514528940615,"location":{"filename":"expressLogger.js","line":43}},"args":{"0":"/api/user/login"},"contextString":"\u001b[36m[Express]\u001b[39m\u001b[31m[::1]\u001b[39m\u001b[32m[POST]\u001b[39m\u001b[90m[DESKTOP]\u001b[39m 2017-12-29T06:29:00.615Z ","argsString":"/api/user/login","message":"\u001b[36m[Express]\u001b[39m\u001b[31m[::1]\u001b[39m\u001b[32m[POST]\u001b[39m\u001b[90m[DESKTOP]\u001b[39m 2017-12-29T06:29:00.615Z /api/user/login"}
{"type":"info","show":{"tags":true,"location":false,"time":true,"date":false},"context":{"tags":[{"msg":"Express","colors":"cyan"},{"msg":"::1","colors":"red"},{"msg":"POST","colors":"green"},{"msg":"DESKTOP","colors":"grey"}],"file":false,"time":1514528974077,"location":{"filename":"expressLogger.js","line":43}},"args":{"0":"/api/user/login"},"contextString":"\u001b[36m[Express]\u001b[39m\u001b[31m[::1]\u001b[39m\u001b[32m[POST]\u001b[39m\u001b[90m[DESKTOP]\u001b[39m 2017-12-29T06:29:34.077Z ","argsString":"/api/user/login","message":"\u001b[36m[Express]\u001b[39m\u001b[31m[::1]\u001b[39m\u001b[32m[POST]\u001b[39m\u001b[90m[DESKTOP]\u001b[39m 2017-12-29T06:29:34.077Z /api/user/login"}
{"type":"info","show":{"tags":true,"location":false,"time":true,"date":false},"context":{"tags":[{"msg":"Express","colors":"cyan"},{"msg":"::1","colors":"red"},{"msg":"POST","colors":"green"},{"msg":"DESKTOP","colors":"grey"}],"file":false,"time":1514529364518,"location":{"filename":"expressLogger.js","line":43}},"args":{"0":"/api/user/auth"},"contextString":"\u001b[36m[Express]\u001b[39m\u001b[31m[::1]\u001b[39m\u001b[32m[POST]\u001b[39m\u001b[90m[DESKTOP]\u001b[39m 2017-12-29T06:36:04.518Z ","argsString":"/api/user/auth","message":"\u001b[36m[Express]\u001b[39m\u001b[31m[::1]\u001b[39m\u001b[32m[POST]\u001b[39m\u001b[90m[DESKTOP]\u001b[39m 2017-12-29T06:36:04.518Z /api/user/auth"}
{"type":"info","show":{"tags":true,"location":false,"time":true,"date":false},"context":{"tags":[{"msg":"Express","colors":"cyan"},{"msg":"::1","colors":"red"},{"msg":"POST","colors":"green"},{"msg":"DESKTOP","colors":"grey"}],"file":false,"time":1514529718053,"location":{"filename":"expressLogger.js","line":43}},"args":{"0":"/api/user/login"},"contextString":"\u001b[36m[Express]\u001b[39m\u001b[31m[::1]\u001b[39m\u001b[32m[POST]\u001b[39m\u001b[90m[DESKTOP]\u001b[39m 2017-12-29T06:41:58.053Z ","argsString":"/api/user/login","message":"\u001b[36m[Express]\u001b[39m\u001b[31m[::1]\u001b[39m\u001b[32m[POST]\u001b[39m\u001b[90m[DESKTOP]\u001b[39m 2017-12-29T06:41:58.053Z /api/user/login"}
{"type":"info","show":{"tags":true,"location":false,"time":true,"date":false},"context":{"tags":[{"msg":"Express","colors":"cyan"},{"msg":"::1","colors":"red"},{"msg":"POST","colors":"green"},{"msg":"DESKTOP","colors":"grey"}],"file":false,"time":1514529737337,"location":{"filename":"expressLogger.js","line":43}},"args":{"0":"/api/user/login"},"contextString":"\u001b[36m[Express]\u001b[39m\u001b[31m[::1]\u001b[39m\u001b[32m[POST]\u001b[39m\u001b[90m[DESKTOP]\u001b[39m 2017-12-29T06:42:17.337Z ","argsString":"/api/user/login","message":"\u001b[36m[Express]\u001b[39m\u001b[31m[::1]\u001b[39m\u001b[32m[POST]\u001b[39m\u001b[90m[DESKTOP]\u001b[39m 2017-12-29T06:42:17.337Z /api/user/login"}
{"type":"info","show":{"tags":true,"location":false,"time":true,"date":false},"context":{"tags":[{"msg":"Express","colors":"cyan"},{"msg":"::1","colors":"red"},{"msg":"POST","colors":"green"},{"msg":"DESKTOP","colors":"grey"}],"file":false,"time":1514529834030,"location":{"filename":"expressLogger.js","line":43}},"args":{"0":"/api/user/login"},"contextString":"\u001b[36m[Express]\u001b[39m\u001b[31m[::1]\u001b[39m\u001b[32m[POST]\u001b[39m\u001b[90m[DESKTOP]\u001b[39m 2017-12-29T06:43:54.030Z ","argsString":"/api/user/login","message":"\u001b[36m[Express]\u001b[39m\u001b[31m[::1]\u001b[39m\u001b[32m[POST]\u001b[39m\u001b[90m[DESKTOP]\u001b[39m 2017-12-29T06:43:54.030Z /api/user/login"}
{"type":"info","show":{"tags":true,"location":false,"time":true,"date":false},"context":{"tags":[{"msg":"Express","colors":"cyan"},{"msg":"::1","colors":"red"},{"msg":"POST","colors":"green"},{"msg":"DESKTOP","colors":"grey"}],"file":false,"time":1514529908767,"location":{"filename":"expressLogger.js","line":43}},"args":{"0":"/api/user/login"},"contextString":"\u001b[36m[Express]\u001b[39m\u001b[31m[::1]\u001b[39m\u001b[32m[POST]\u001b[39m\u001b[90m[DESKTOP]\u001b[39m 2017-12-29T06:45:08.767Z ","argsString":"/api/user/login","message":"\u001b[36m[Express]\u001b[39m\u001b[31m[::1]\u001b[39m\u001b[32m[POST]\u001b[39m\u001b[90m[DESKTOP]\u001b[39m 2017-12-29T06:45:08.767Z /api/user/login"}
{"type":"info","show":{"tags":true,"location":false,"time":true,"date":false},"context":{"tags":[{"msg":"Express","colors":"cyan"},{"msg":"::1","colors":"red"},{"msg":"POST","colors":"green"},{"msg":"DESKTOP","colors":"grey"}],"file":false,"time":1514529944195,"location":{"filename":"expressLogger.js","line":43}},"args":{"0":"/api/user/login"},"contextString":"\u001b[36m[Express]\u001b[39m\u001b[31m[::1]\u001b[39m\u001b[32m[POST]\u001b[39m\u001b[90m[DESKTOP]\u001b[39m 2017-12-29T06:45:44.195Z ","argsString":"/api/user/login","message":"\u001b[36m[Express]\u001b[39m\u001b[31m[::1]\u001b[39m\u001b[32m[POST]\u001b[39m\u001b[90m[DESKTOP]\u001b[39m 2017-12-29T06:45:44.195Z /api/user/login"}
{"type":"info","show":{"tags":true,"location":false,"time":true,"date":false},"context":{"tags":[{"msg":"Express","colors":"cyan"},{"msg":"::1","colors":"red"},{"msg":"POST","colors":"green"},{"msg":"DESKTOP","colors":"grey"}],"file":false,"time":1514529971720,"location":{"filename":"expressLogger.js","line":43}},"args":{"0":"/api/user/login"},"contextString":"\u001b[36m[Express]\u001b[39m\u001b[31m[::1]\u001b[39m\u001b[32m[POST]\u001b[39m\u001b[90m[DESKTOP]\u001b[39m 2017-12-29T06:46:11.720Z ","argsString":"/api/user/login","message":"\u001b[36m[Express]\u001b[39m\u001b[31m[::1]\u001b[39m\u001b[32m[POST]\u001b[39m\u001b[90m[DESKTOP]\u001b[39m 2017-12-29T06:46:11.720Z /api/user/login"}
{"type":"info","show":{"tags":true,"location":false,"time":true,"date":false},"context":{"tags":[{"msg":"Express","colors":"cyan"},{"msg":"::1","colors":"red"},{"msg":"POST","colors":"green"},{"msg":"DESKTOP","colors":"grey"}],"file":false,"time":1514530187952,"location":{"filename":"expressLogger.js","line":43}},"args":{"0":"/api/user/login"},"contextString":"\u001b[36m[Express]\u001b[39m\u001b[31m[::1]\u001b[39m\u001b[32m[POST]\u001b[39m\u001b[90m[DESKTOP]\u001b[39m 2017-12-29T06:49:47.952Z ","argsString":"/api/user/login","message":"\u001b[36m[Express]\u001b[39m\u001b[31m[::1]\u001b[39m\u001b[32m[POST]\u001b[39m\u001b[90m[DESKTOP]\u001b[39m 2017-12-29T06:49:47.952Z /api/user/login"}
{"type":"info","show":{"tags":true,"location":false,"time":true,"date":false},"context":{"tags":[{"msg":"Express","colors":"cyan"},{"msg":"::1","colors":"red"},{"msg":"POST","colors":"green"},{"msg":"DESKTOP","colors":"grey"}],"file":false,"time":1514530189649,"location":{"filename":"expressLogger.js","line":43}},"args":{"0":"/api/user/auth"},"contextString":"\u001b[36m[Express]\u001b[39m\u001b[31m[::1]\u001b[39m\u001b[32m[POST]\u001b[39m\u001b[90m[DESKTOP]\u001b[39m 2017-12-29T06:49:49.649Z ","argsString":"/api/user/auth","message":"\u001b[36m[Express]\u001b[39m\u001b[31m[::1]\u001b[39m\u001b[32m[POST]\u001b[39m\u001b[90m[DESKTOP]\u001b[39m 2017-12-29T06:49:49.649Z /api/user/auth"}
{"type":"info","show":{"tags":true,"location":false,"time":true,"date":false},"context":{"tags":[{"msg":"Express","colors":"cyan"},{"msg":"::1","colors":"red"},{"msg":"POST","colors":"green"},{"msg":"DESKTOP","colors":"grey"}],"file":false,"time":1514530191754,"location":{"filename":"expressLogger.js","line":43}},"args":{"0":"/api/user/logout"},"contextString":"\u001b[36m[Express]\u001b[39m\u001b[31m[::1]\u001b[39m\u001b[32m[POST]\u001b[39m\u001b[90m[DESKTOP]\u001b[39m 2017-12-29T06:49:51.754Z ","argsString":"/api/user/logout","message":"\u001b[36m[Express]\u001b[39m\u001b[31m[::1]\u001b[39m\u001b[32m[POST]\u001b[39m\u001b[90m[DESKTOP]\u001b[39m 2017-12-29T06:49:51.754Z /api/user/logout"}
{"type":"info","show":{"tags":true,"location":false,"time":true,"date":false},"context":{"tags":[{"msg":"Express","colors":"cyan"},{"msg":"::1","colors":"red"},{"msg":"POST","colors":"green"},{"msg":"DESKTOP","colors":"grey"}],"file":false,"time":1514530195457,"location":{"filename":"expressLogger.js","line":43}},"args":{"0":"/api/user/login"},"contextString":"\u001b[36m[Express]\u001b[39m\u001b[31m[::1]\u001b[39m\u001b[32m[POST]\u001b[39m\u001b[90m[DESKTOP]\u001b[39m 2017-12-29T06:49:55.457Z ","argsString":"/api/user/login","message":"\u001b[36m[Express]\u001b[39m\u001b[31m[::1]\u001b[39m\u001b[32m[POST]\u001b[39m\u001b[90m[DESKTOP]\u001b[39m 2017-12-29T06:49:55.457Z /api/user/login"}
{"type":"info","show":{"tags":true,"location":false,"time":true,"date":false},"context":{"tags":[{"msg":"Express","colors":"cyan"},{"msg":"::1","colors":"red"},{"msg":"POST","colors":"green"},{"msg":"DESKTOP","colors":"grey"}],"file":false,"time":1514530197971,"location":{"filename":"expressLogger.js","line":43}},"args":{"0":"/api/user/adduser"},"contextString":"\u001b[36m[Express]\u001b[39m\u001b[31m[::1]\u001b[39m\u001b[32m[POST]\u001b[39m\u001b[90m[DESKTOP]\u001b[39m 2017-12-29T06:49:57.971Z ","argsString":"/api/user/adduser","message":"\u001b[36m[Express]\u001b[39m\u001b[31m[::1]\u001b[39m\u001b[32m[POST]\u001b[39m\u001b[90m[DESKTOP]\u001b[39m 2017-12-29T06:49:57.971Z /api/user/adduser"}
{"type":"info","show":{"tags":true,"location":false,"time":true,"date":false},"context":{"tags":[{"msg":"Express","colors":"cyan"},{"msg":"::1","colors":"red"},{"msg":"POST","colors":"green"},{"msg":"DESKTOP","colors":"grey"}],"file":false,"time":1514530430357,"location":{"filename":"expressLogger.js","line":43}},"args":{"0":"/api/user/login"},"contextString":"\u001b[36m[Express]\u001b[39m\u001b[31m[::1]\u001b[39m\u001b[32m[POST]\u001b[39m\u001b[90m[DESKTOP]\u001b[39m 2017-12-29T06:53:50.357Z ","argsString":"/api/user/login","message":"\u001b[36m[Express]\u001b[39m\u001b[31m[::1]\u001b[39m\u001b[32m[POST]\u001b[39m\u001b[90m[DESKTOP]\u001b[39m 2017-12-29T06:53:50.357Z /api/user/login"}
{"type":"info","show":{"tags":true,"location":false,"time":true,"date":false},"context":{"tags":[{"msg":"Express","colors":"cyan"},{"msg":"::1","colors":"red"},{"msg":"POST","colors":"green"},{"msg":"DESKTOP","colors":"grey"}],"file":false,"time":1514530438994,"location":{"filename":"expressLogger.js","line":43}},"args":{"0":"/api/user/auth"},"contextString":"\u001b[36m[Express]\u001b[39m\u001b[31m[::1]\u001b[39m\u001b[32m[POST]\u001b[39m\u001b[90m[DESKTOP]\u001b[39m 2017-12-29T06:53:58.994Z ","argsString":"/api/user/auth","message":"\u001b[36m[Express]\u001b[39m\u001b[31m[::1]\u001b[39m\u001b[32m[POST]\u001b[39m\u001b[90m[DESKTOP]\u001b[39m 2017-12-29T06:53:58.994Z /api/user/auth"}
{"type":"info","show":{"tags":true,"location":false,"time":true,"date":false},"context":{"tags":[{"msg":"Express","colors":"cyan"},{"msg":"::1","colors":"red"},{"msg":"POST","colors":"green"},{"msg":"DESKTOP","colors":"grey"}],"file":false,"time":1514530446669,"location":{"filename":"expressLogger.js","line":43}},"args":{"0":"/api/user/logout"},"contextString":"\u001b[36m[Express]\u001b[39m\u001b[31m[::1]\u001b[39m\u001b[32m[POST]\u001b[39m\u001b[90m[DESKTOP]\u001b[39m 2017-12-29T06:54:06.669Z ","argsString":"/api/user/logout","message":"\u001b[36m[Express]\u001b[39m\u001b[31m[::1]\u001b[39m\u001b[32m[POST]\u001b[39m\u001b[90m[DESKTOP]\u001b[39m 2017-12-29T06:54:06.669Z /api/user/logout"}
{"type":"info","show":{"tags":true,"location":false,"time":true,"date":false},"context":{"tags":[{"msg":"Express","colors":"cyan"},{"msg":"::1","colors":"red"},{"msg":"POST","colors":"green"},{"msg":"DESKTOP","colors":"grey"}],"file":false,"time":1514530680800,"location":{"filename":"expressLogger.js","line":43}},"args":{"0":"/api/user/login"},"contextString":"\u001b[36m[Express]\u001b[39m\u001b[31m[::1]\u001b[39m\u001b[32m[POST]\u001b[39m\u001b[90m[DESKTOP]\u001b[39m 2017-12-29T06:58:00.800Z ","argsString":"/api/user/login","message":"\u001b[36m[Express]\u001b[39m\u001b[31m[::1]\u001b[39m\u001b[32m[POST]\u001b[39m\u001b[90m[DESKTOP]\u001b[39m 2017-12-29T06:58:00.800Z /api/user/login"}
{"type":"info","show":{"tags":true,"location":false,"time":true,"date":false},"context":{"tags":[{"msg":"Express","colors":"cyan"},{"msg":"::1","colors":"red"},{"msg":"POST","colors":"green"},{"msg":"DESKTOP","colors":"grey"}],"file":false,"time":1514542428697,"location":{"filename":"expressLogger.js","line":43}},"args":{"0":"/api/user/login"},"contextString":"\u001b[36m[Express]\u001b[39m\u001b[31m[::1]\u001b[39m\u001b[32m[POST]\u001b[39m\u001b[90m[DESKTOP]\u001b[39m 2017-12-29T10:13:48.697Z ","argsString":"/api/user/login","message":"\u001b[36m[Express]\u001b[39m\u001b[31m[::1]\u001b[39m\u001b[32m[POST]\u001b[39m\u001b[90m[DESKTOP]\u001b[39m 2017-12-29T10:13:48.697Z /api/user/login"}
{"type":"info","show":{"tags":true,"location":false,"time":true,"date":false},"context":{"tags":[{"msg":"Express","colors":"cyan"},{"msg":"::1","colors":"red"},{"msg":"POST","colors":"green"},{"msg":"DESKTOP","colors":"grey"}],"file":false,"time":1514542533304,"location":{"filename":"expressLogger.js","line":43}},"args":{"0":"/api/user/login"},"contextString":"\u001b[36m[Express]\u001b[39m\u001b[31m[::1]\u001b[39m\u001b[32m[POST]\u001b[39m\u001b[90m[DESKTOP]\u001b[39m 2017-12-29T10:15:33.304Z ","argsString":"/api/user/login","message":"\u001b[36m[Express]\u001b[39m\u001b[31m[::1]\u001b[39m\u001b[32m[POST]\u001b[39m\u001b[90m[DESKTOP]\u001b[39m 2017-12-29T10:15:33.304Z /api/user/login"}
{"type":"info","show":{"tags":true,"location":false,"time":true,"date":false},"context":{"tags":[{"msg":"Express","colors":"cyan"},{"msg":"::1","colors":"red"},{"msg":"POST","colors":"green"},{"msg":"DESKTOP","colors":"grey"}],"file":false,"time":1514542888524,"location":{"filename":"expressLogger.js","line":43}},"args":{"0":"/api/user/login"},"contextString":"\u001b[36m[Express]\u001b[39m\u001b[31m[::1]\u001b[39m\u001b[32m[POST]\u001b[39m\u001b[90m[DESKTOP]\u001b[39m 2017-12-29T10:21:28.524Z ","argsString":"/api/user/login","message":"\u001b[36m[Express]\u001b[39m\u001b[31m[::1]\u001b[39m\u001b[32m[POST]\u001b[39m\u001b[90m[DESKTOP]\u001b[39m 2017-12-29T10:21:28.524Z /api/user/login"}
{"type":"info","show":{"tags":true,"location":false,"time":true,"date":false},"context":{"tags":[{"msg":"Express","colors":"cyan"},{"msg":"::1","colors":"red"},{"msg":"POST","colors":"green"},{"msg":"DESKTOP","colors":"grey"}],"file":false,"time":1514542949033,"location":{"filename":"expressLogger.js","line":43}},"args":{"0":"/api/user/login"},"contextString":"\u001b[36m[Express]\u001b[39m\u001b[31m[::1]\u001b[39m\u001b[32m[POST]\u001b[39m\u001b[90m[DESKTOP]\u001b[39m 2017-12-29T10:22:29.033Z ","argsString":"/api/user/login","message":"\u001b[36m[Express]\u001b[39m\u001b[31m[::1]\u001b[39m\u001b[32m[POST]\u001b[39m\u001b[90m[DESKTOP]\u001b[39m 2017-12-29T10:22:29.033Z /api/user/login"}
{"type":"info","show":{"tags":true,"location":false,"time":true,"date":false},"context":{"tags":[{"msg":"Express","colors":"cyan"},{"msg":"::1","colors":"red"},{"msg":"POST","colors":"green"},{"msg":"DESKTOP","colors":"grey"}],"file":false,"time":1514542957506,"location":{"filename":"expressLogger.js","line":43}},"args":{"0":"/api/user/login"},"contextString":"\u001b[36m[Express]\u001b[39m\u001b[31m[::1]\u001b[39m\u001b[32m[POST]\u001b[39m\u001b[90m[DESKTOP]\u001b[39m 2017-12-29T10:22:37.506Z ","argsString":"/api/user/login","message":"\u001b[36m[Express]\u001b[39m\u001b[31m[::1]\u001b[39m\u001b[32m[POST]\u001b[39m\u001b[90m[DESKTOP]\u001b[39m 2017-12-29T10:22:37.506Z /api/user/login"}
{"type":"info","show":{"tags":true,"location":false,"time":true,"date":false},"context":{"tags":[{"msg":"Express","colors":"cyan"},{"msg":"::1","colors":"red"},{"msg":"POST","colors":"green"},{"msg":"DESKTOP","colors":"grey"}],"file":false,"time":1514542990554,"location":{"filename":"expressLogger.js","line":43}},"args":{"0":"/api/user/login"},"contextString":"\u001b[36m[Express]\u001b[39m\u001b[31m[::1]\u001b[39m\u001b[32m[POST]\u001b[39m\u001b[90m[DESKTOP]\u001b[39m 2017-12-29T10:23:10.554Z ","argsString":"/api/user/login","message":"\u001b[36m[Express]\u001b[39m\u001b[31m[::1]\u001b[39m\u001b[32m[POST]\u001b[39m\u001b[90m[DESKTOP]\u001b[39m 2017-12-29T10:23:10.554Z /api/user/login"}
{"type":"info","show":{"tags":true,"location":false,"time":true,"date":false},"context":{"tags":[{"msg":"Express","colors":"cyan"},{"msg":"::1","colors":"red"},{"msg":"POST","colors":"green"},{"msg":"DESKTOP","colors":"grey"}],"file":false,"time":1514552558354,"location":{"filename":"expressLogger.js","line":43}},"args":{"0":"/api/user/login"},"contextString":"\u001b[36m[Express]\u001b[39m\u001b[31m[::1]\u001b[39m\u001b[32m[POST]\u001b[39m\u001b[90m[DESKTOP]\u001b[39m 2017-12-29T13:02:38.354Z ","argsString":"/api/user/login","message":"\u001b[36m[Express]\u001b[39m\u001b[31m[::1]\u001b[39m\u001b[32m[POST]\u001b[39m\u001b[90m[DESKTOP]\u001b[39m 2017-12-29T13:02:38.354Z /api/user/login"}
{"type":"info","show":{"tags":true,"location":false,"time":true,"date":false},"context":{"tags":[{"msg":"Express","colors":"cyan"},{"msg":"::1","colors":"red"},{"msg":"POST","colors":"green"},{"msg":"DESKTOP","colors":"grey"}],"file":false,"time":1514554530215,"location":{"filename":"expressLogger.js","line":43}},"args":{"0":"/api/user/login"},"contextString":"\u001b[36m[Express]\u001b[39m\u001b[31m[::1]\u001b[39m\u001b[32m[POST]\u001b[39m\u001b[90m[DESKTOP]\u001b[39m 2017-12-29T13:35:30.215Z ","argsString":"/api/user/login","message":"\u001b[36m[Express]\u001b[39m\u001b[31m[::1]\u001b[39m\u001b[32m[POST]\u001b[39m\u001b[90m[DESKTOP]\u001b[39m 2017-12-29T13:35:30.215Z /api/user/login"}
{"type":"info","show":{"tags":true,"location":false,"time":true,"date":false},"context":{"tags":[{"msg":"Express","colors":"cyan"},{"msg":"::1","colors":"red"},{"msg":"POST","colors":"green"},{"msg":"DESKTOP","colors":"grey"}],"file":false,"time":1514554551359,"location":{"filename":"expressLogger.js","line":43}},"args":{"0":"/api/user/auth"},"contextString":"\u001b[36m[Express]\u001b[39m\u001b[31m[::1]\u001b[39m\u001b[32m[POST]\u001b[39m\u001b[90m[DESKTOP]\u001b[39m 2017-12-29T13:35:51.359Z ","argsString":"/api/user/auth","message":"\u001b[36m[Express]\u001b[39m\u001b[31m[::1]\u001b[39m\u001b[32m[POST]\u001b[39m\u001b[90m[DESKTOP]\u001b[39m 2017-12-29T13:35:51.359Z /api/user/auth"}
{"type":"info","show":{"tags":true,"location":false,"time":true,"date":false},"context":{"tags":[{"msg":"Express","colors":"cyan"},{"msg":"::1","colors":"red"},{"msg":"POST","colors":"green"},{"msg":"DESKTOP","colors":"grey"}],"file":false,"time":1514555485487,"location":{"filename":"expressLogger.js","line":43}},"args":{"0":"/api/user/login"},"contextString":"\u001b[36m[Express]\u001b[39m\u001b[31m[::1]\u001b[39m\u001b[32m[POST]\u001b[39m\u001b[90m[DESKTOP]\u001b[39m 2017-12-29T13:51:25.487Z ","argsString":"/api/user/login","message":"\u001b[36m[Express]\u001b[39m\u001b[31m[::1]\u001b[39m\u001b[32m[POST]\u001b[39m\u001b[90m[DESKTOP]\u001b[39m 2017-12-29T13:51:25.487Z /api/user/login"}
{"type":"info","show":{"tags":true,"location":false,"time":true,"date":false},"context":{"tags":[{"msg":"Express","colors":"cyan"},{"msg":"::1","colors":"red"},{"msg":"POST","colors":"green"},{"msg":"DESKTOP","colors":"grey"}],"file":false,"time":1514555486803,"location":{"filename":"expressLogger.js","line":43}},"args":{"0":"/api/user/auth"},"contextString":"\u001b[36m[Express]\u001b[39m\u001b[31m[::1]\u001b[39m\u001b[32m[POST]\u001b[39m\u001b[90m[DESKTOP]\u001b[39m 2017-12-29T13:51:26.803Z ","argsString":"/api/user/auth","message":"\u001b[36m[Express]\u001b[39m\u001b[31m[::1]\u001b[39m\u001b[32m[POST]\u001b[39m\u001b[90m[DESKTOP]\u001b[39m 2017-12-29T13:51:26.803Z /api/user/auth"}
{"type":"info","show":{"tags":true,"location":false,"time":true,"date":false},"context":{"tags":[{"msg":"Express","colors":"cyan"},{"msg":"::1","colors":"red"},{"msg":"POST","colors":"green"},{"msg":"DESKTOP","colors":"grey"}],"file":false,"time":1514555548550,"location":{"filename":"expressLogger.js","line":43}},"args":{"0":"/api/user/login"},"contextString":"\u001b[36m[Express]\u001b[39m\u001b[31m[::1]\u001b[39m\u001b[32m[POST]\u001b[39m\u001b[90m[DESKTOP]\u001b[39m 2017-12-29T13:52:28.550Z ","argsString":"/api/user/login","message":"\u001b[36m[Express]\u001b[39m\u001b[31m[::1]\u001b[39m\u001b[32m[POST]\u001b[39m\u001b[90m[DESKTOP]\u001b[39m 2017-12-29T13:52:28.550Z /api/user/login"}
{"type":"info","show":{"tags":true,"location":false,"time":true,"date":false},"context":{"tags":[{"msg":"Express","colors":"cyan"},{"msg":"::1","colors":"red"},{"msg":"POST","colors":"green"},{"msg":"DESKTOP","colors":"grey"}],"file":false,"time":1514555551095,"location":{"filename":"expressLogger.js","line":43}},"args":{"0":"/api/user/auth"},"contextString":"\u001b[36m[Express]\u001b[39m\u001b[31m[::1]\u001b[39m\u001b[32m[POST]\u001b[39m\u001b[90m[DESKTOP]\u001b[39m 2017-12-29T13:52:31.095Z ","argsString":"/api/user/auth","message":"\u001b[36m[Express]\u001b[39m\u001b[31m[::1]\u001b[39m\u001b[32m[POST]\u001b[39m\u001b[90m[DESKTOP]\u001b[39m 2017-12-29T13:52:31.095Z /api/user/auth"}
{"type":"info","show":{"tags":true,"location":false,"time":true,"date":false},"context":{"tags":[{"msg":"Express","colors":"cyan"},{"msg":"::1","colors":"red"},{"msg":"POST","colors":"green"},{"msg":"DESKTOP","colors":"grey"}],"file":false,"time":1514555577380,"location":{"filename":"expressLogger.js","line":43}},"args":{"0":"/api/user/login"},"contextString":"\u001b[36m[Express]\u001b[39m\u001b[31m[::1]\u001b[39m\u001b[32m[POST]\u001b[39m\u001b[90m[DESKTOP]\u001b[39m 2017-12-29T13:52:57.380Z ","argsString":"/api/user/login","message":"\u001b[36m[Express]\u001b[39m\u001b[31m[::1]\u001b[39m\u001b[32m[POST]\u001b[39m\u001b[90m[DESKTOP]\u001b[39m 2017-12-29T13:52:57.380Z /api/user/login"}
{"type":"info","show":{"tags":true,"location":false,"time":true,"date":false},"context":{"tags":[{"msg":"Express","colors":"cyan"},{"msg":"::1","colors":"red"},{"msg":"POST","colors":"green"},{"msg":"DESKTOP","colors":"grey"}],"file":false,"time":1514555578765,"location":{"filename":"expressLogger.js","line":43}},"args":{"0":"/api/user/auth"},"contextString":"\u001b[36m[Express]\u001b[39m\u001b[31m[::1]\u001b[39m\u001b[32m[POST]\u001b[39m\u001b[90m[DESKTOP]\u001b[39m 2017-12-29T13:52:58.765Z ","argsString":"/api/user/auth","message":"\u001b[36m[Express]\u001b[39m\u001b[31m[::1]\u001b[39m\u001b[32m[POST]\u001b[39m\u001b[90m[DESKTOP]\u001b[39m 2017-12-29T13:52:58.765Z /api/user/auth"}
{"type":"info","show":{"tags":true,"location":false,"time":true,"date":false},"context":{"tags":[{"msg":"Express","colors":"cyan"},{"msg":"::1","colors":"red"},{"msg":"POST","colors":"green"},{"msg":"DESKTOP","colors":"grey"}],"file":false,"time":1514555637374,"location":{"filename":"expressLogger.js","line":43}},"args":{"0":"/api/user/login"},"contextString":"\u001b[36m[Express]\u001b[39m\u001b[31m[::1]\u001b[39m\u001b[32m[POST]\u001b[39m\u001b[90m[DESKTOP]\u001b[39m 2017-12-29T13:53:57.374Z ","argsString":"/api/user/login","message":"\u001b[36m[Express]\u001b[39m\u001b[31m[::1]\u001b[39m\u001b[32m[POST]\u001b[39m\u001b[90m[DESKTOP]\u001b[39m 2017-12-29T13:53:57.374Z /api/user/login"}
{"type":"info","show":{"tags":true,"location":false,"time":true,"date":false},"context":{"tags":[{"msg":"Express","colors":"cyan"},{"msg":"::1","colors":"red"},{"msg":"POST","colors":"green"},{"msg":"DESKTOP","colors":"grey"}],"file":false,"time":1514555638341,"location":{"filename":"expressLogger.js","line":43}},"args":{"0":"/api/user/auth"},"contextString":"\u001b[36m[Express]\u001b[39m\u001b[31m[::1]\u001b[39m\u001b[32m[POST]\u001b[39m\u001b[90m[DESKTOP]\u001b[39m 2017-12-29T13:53:58.341Z ","argsString":"/api/user/auth","message":"\u001b[36m[Express]\u001b[39m\u001b[31m[::1]\u001b[39m\u001b[32m[POST]\u001b[39m\u001b[90m[DESKTOP]\u001b[39m 2017-12-29T13:53:58.341Z /api/user/auth"}
{"type":"info","show":{"tags":true,"location":false,"time":true,"date":false},"context":{"tags":[{"msg":"Express","colors":"cyan"},{"msg":"::1","colors":"red"},{"msg":"POST","colors":"green"},{"msg":"DESKTOP","colors":"grey"}],"file":false,"time":1514555655941,"location":{"filename":"expressLogger.js","line":43}},"args":{"0":"/api/user/auth"},"contextString":"\u001b[36m[Express]\u001b[39m\u001b[31m[::1]\u001b[39m\u001b[32m[POST]\u001b[39m\u001b[90m[DESKTOP]\u001b[39m 2017-12-29T13:54:15.941Z ","argsString":"/api/user/auth","message":"\u001b[36m[Express]\u001b[39m\u001b[31m[::1]\u001b[39m\u001b[32m[POST]\u001b[39m\u001b[90m[DESKTOP]\u001b[39m 2017-12-29T13:54:15.941Z /api/user/auth"}
{"type":"info","show":{"tags":true,"location":false,"time":true,"date":false},"context":{"tags":[{"msg":"Express","colors":"cyan"},{"msg":"::1","colors":"red"},{"msg":"POST","colors":"green"},{"msg":"DESKTOP","colors":"grey"}],"file":false,"time":1514556075656,"location":{"filename":"expressLogger.js","line":43}},"args":{"0":"/api/user/login"},"contextString":"\u001b[36m[Express]\u001b[39m\u001b[31m[::1]\u001b[39m\u001b[32m[POST]\u001b[39m\u001b[90m[DESKTOP]\u001b[39m 2017-12-29T14:01:15.656Z ","argsString":"/api/user/login","message":"\u001b[36m[Express]\u001b[39m\u001b[31m[::1]\u001b[39m\u001b[32m[POST]\u001b[39m\u001b[90m[DESKTOP]\u001b[39m 2017-12-29T14:01:15.656Z /api/user/login"}
{"type":"info","show":{"tags":true,"location":false,"time":true,"date":false},"context":{"tags":[{"msg":"Express","colors":"cyan"},{"msg":"::1","colors":"red"},{"msg":"POST","colors":"green"},{"msg":"DESKTOP","colors":"grey"}],"file":false,"time":1514556095512,"location":{"filename":"expressLogger.js","line":43}},"args":{"0":"/api/user/auth"},"contextString":"\u001b[36m[Express]\u001b[39m\u001b[31m[::1]\u001b[39m\u001b[32m[POST]\u001b[39m\u001b[90m[DESKTOP]\u001b[39m 2017-12-29T14:01:35.512Z ","argsString":"/api/user/auth","message":"\u001b[36m[Express]\u001b[39m\u001b[31m[::1]\u001b[39m\u001b[32m[POST]\u001b[39m\u001b[90m[DESKTOP]\u001b[39m 2017-12-29T14:01:35.512Z /api/user/auth"}
{"type":"info","show":{"tags":true,"location":false,"time":true,"date":false},"context":{"tags":[{"msg":"Express","colors":"cyan"},{"msg":"::1","colors":"red"},{"msg":"POST","colors":"green"},{"msg":"DESKTOP","colors":"grey"}],"file":false,"time":1514556635391,"location":{"filename":"expressLogger.js","line":43}},"args":{"0":"/api/user/login"},"contextString":"\u001b[36m[Express]\u001b[39m\u001b[31m[::1]\u001b[39m\u001b[32m[POST]\u001b[39m\u001b[90m[DESKTOP]\u001b[39m 2017-12-29T14:10:35.391Z ","argsString":"/api/user/login","message":"\u001b[36m[Express]\u001b[39m\u001b[31m[::1]\u001b[39m\u001b[32m[POST]\u001b[39m\u001b[90m[DESKTOP]\u001b[39m 2017-12-29T14:10:35.391Z /api/user/login"}
{"type":"info","show":{"tags":true,"location":false,"time":true,"date":false},"context":{"tags":[{"msg":"Express","colors":"cyan"},{"msg":"::1","colors":"red"},{"msg":"POST","colors":"green"},{"msg":"DESKTOP","colors":"grey"}],"file":false,"time":1514556636727,"location":{"filename":"expressLogger.js","line":43}},"args":{"0":"/api/user/auth"},"contextString":"\u001b[36m[Express]\u001b[39m\u001b[31m[::1]\u001b[39m\u001b[32m[POST]\u001b[39m\u001b[90m[DESKTOP]\u001b[39m 2017-12-29T14:10:36.727Z ","argsString":"/api/user/auth","message":"\u001b[36m[Express]\u001b[39m\u001b[31m[::1]\u001b[39m\u001b[32m[POST]\u001b[39m\u001b[90m[DESKTOP]\u001b[39m 2017-12-29T14:10:36.727Z /api/user/auth"}
{"type":"info","show":{"tags":true,"location":false,"time":true,"date":false},"context":{"tags":[{"msg":"Express","colors":"cyan"},{"msg":"::1","colors":"red"},{"msg":"POST","colors":"green"},{"msg":"DESKTOP","colors":"grey"}],"file":false,"time":1514556696751,"location":{"filename":"expressLogger.js","line":43}},"args":{"0":"/api/user/auth"},"contextString":"\u001b[36m[Express]\u001b[39m\u001b[31m[::1]\u001b[39m\u001b[32m[POST]\u001b[39m\u001b[90m[DESKTOP]\u001b[39m 2017-12-29T14:11:36.751Z ","argsString":"/api/user/auth","message":"\u001b[36m[Express]\u001b[39m\u001b[31m[::1]\u001b[39m\u001b[32m[POST]\u001b[39m\u001b[90m[DESKTOP]\u001b[39m 2017-12-29T14:11:36.751Z /api/user/auth"}
{"type":"info","show":{"tags":true,"location":false,"time":true,"date":false},"context":{"tags":[{"msg":"Express","colors":"cyan"},{"msg":"::1","colors":"red"},{"msg":"POST","colors":"green"},{"msg":"DESKTOP","colors":"grey"}],"file":false,"time":1514556698193,"location":{"filename":"expressLogger.js","line":43}},"args":{"0":"/api/user/auth"},"contextString":"\u001b[36m[Express]\u001b[39m\u001b[31m[::1]\u001b[39m\u001b[32m[POST]\u001b[39m\u001b[90m[DESKTOP]\u001b[39m 2017-12-29T14:11:38.193Z ","argsString":"/api/user/auth","message":"\u001b[36m[Express]\u001b[39m\u001b[31m[::1]\u001b[39m\u001b[32m[POST]\u001b[39m\u001b[90m[DESKTOP]\u001b[39m 2017-12-29T14:11:38.193Z /api/user/auth"}
{"type":"info","show":{"tags":true,"location":false,"time":true,"date":false},"context":{"tags":[{"msg":"Express","colors":"cyan"},{"msg":"::1","colors":"red"},{"msg":"POST","colors":"green"},{"msg":"DESKTOP","colors":"grey"}],"file":false,"time":1514556700550,"location":{"filename":"expressLogger.js","line":43}},"args":{"0":"/api/user/auth"},"contextString":"\u001b[36m[Express]\u001b[39m\u001b[31m[::1]\u001b[39m\u001b[32m[POST]\u001b[39m\u001b[90m[DESKTOP]\u001b[39m 2017-12-29T14:11:40.550Z ","argsString":"/api/user/auth","message":"\u001b[36m[Express]\u001b[39m\u001b[31m[::1]\u001b[39m\u001b[32m[POST]\u001b[39m\u001b[90m[DESKTOP]\u001b[39m 2017-12-29T14:11:40.550Z /api/user/auth"}
{"type":"info","show":{"tags":true,"location":false,"time":true,"date":false},"context":{"tags":[{"msg":"Express","colors":"cyan"},{"msg":"::1","colors":"red"},{"msg":"POST","colors":"green"},{"msg":"DESKTOP","colors":"grey"}],"file":false,"time":1514556700554,"location":{"filename":"expressLogger.js","line":43}},"args":{"0":"/api/user/logout"},"contextString":"\u001b[36m[Express]\u001b[39m\u001b[31m[::1]\u001b[39m\u001b[32m[POST]\u001b[39m\u001b[90m[DESKTOP]\u001b[39m 2017-12-29T14:11:40.554Z ","argsString":"/api/user/logout","message":"\u001b[36m[Express]\u001b[39m\u001b[31m[::1]\u001b[39m\u001b[32m[POST]\u001b[39m\u001b[90m[DESKTOP]\u001b[39m 2017-12-29T14:11:40.554Z /api/user/logout"}
{"type":"info","show":{"tags":true,"location":false,"time":true,"date":false},"context":{"tags":[{"msg":"Express","colors":"cyan"},{"msg":"::1","colors":"red"},{"msg":"POST","colors":"green"},{"msg":"DESKTOP","colors":"grey"}],"file":false,"time":1514556740632,"location":{"filename":"expressLogger.js","line":43}},"args":{"0":"/api/user/auth"},"contextString":"\u001b[36m[Express]\u001b[39m\u001b[31m[::1]\u001b[39m\u001b[32m[POST]\u001b[39m\u001b[90m[DESKTOP]\u001b[39m 2017-12-29T14:12:20.632Z ","argsString":"/api/user/auth","message":"\u001b[36m[Express]\u001b[39m\u001b[31m[::1]\u001b[39m\u001b[32m[POST]\u001b[39m\u001b[90m[DESKTOP]\u001b[39m 2017-12-29T14:12:20.632Z /api/user/auth"}
{"type":"info","show":{"tags":true,"location":false,"time":true,"date":false},"context":{"tags":[{"msg":"Express","colors":"cyan"},{"msg":"::1","colors":"red"},{"msg":"POST","colors":"green"},{"msg":"DESKTOP","colors":"grey"}],"file":false,"time":1514556774030,"location":{"filename":"expressLogger.js","line":43}},"args":{"0":"/api/user/auth"},"contextString":"\u001b[36m[Express]\u001b[39m\u001b[31m[::1]\u001b[39m\u001b[32m[POST]\u001b[39m\u001b[90m[DESKTOP]\u001b[39m 2017-12-29T14:12:54.030Z ","argsString":"/api/user/auth","message":"\u001b[36m[Express]\u001b[39m\u001b[31m[::1]\u001b[39m\u001b[32m[POST]\u001b[39m\u001b[90m[DESKTOP]\u001b[39m 2017-12-29T14:12:54.030Z /api/user/auth"}
{"type":"info","show":{"tags":true,"location":false,"time":true,"date":false},"context":{"tags":[{"msg":"Express","colors":"cyan"},{"msg":"::1","colors":"red"},{"msg":"POST","colors":"green"},{"msg":"DESKTOP","colors":"grey"}],"file":false,"time":1514556774043,"location":{"filename":"expressLogger.js","line":43}},"args":{"0":"/api/user/logout"},"contextString":"\u001b[36m[Express]\u001b[39m\u001b[31m[::1]\u001b[39m\u001b[32m[POST]\u001b[39m\u001b[90m[DESKTOP]\u001b[39m 2017-12-29T14:12:54.043Z ","argsString":"/api/user/logout","message":"\u001b[36m[Express]\u001b[39m\u001b[31m[::1]\u001b[39m\u001b[32m[POST]\u001b[39m\u001b[90m[DESKTOP]\u001b[39m 2017-12-29T14:12:54.043Z /api/user/logout"}
{"type":"info","show":{"tags":true,"location":false,"time":true,"date":false},"context":{"tags":[{"msg":"Express","colors":"cyan"},{"msg":"::1","colors":"red"},{"msg":"POST","colors":"green"},{"msg":"DESKTOP","colors":"grey"}],"file":false,"time":1514556803245,"location":{"filename":"expressLogger.js","line":43}},"args":{"0":"/api/user/login"},"contextString":"\u001b[36m[Express]\u001b[39m\u001b[31m[::1]\u001b[39m\u001b[32m[POST]\u001b[39m\u001b[90m[DESKTOP]\u001b[39m 2017-12-29T14:13:23.245Z ","argsString":"/api/user/login","message":"\u001b[36m[Express]\u001b[39m\u001b[31m[::1]\u001b[39m\u001b[32m[POST]\u001b[39m\u001b[90m[DESKTOP]\u001b[39m 2017-12-29T14:13:23.245Z /api/user/login"}
{"type":"info","show":{"tags":true,"location":false,"time":true,"date":false},"context":{"tags":[{"msg":"Express","colors":"cyan"},{"msg":"::1","colors":"red"},{"msg":"POST","colors":"green"},{"msg":"DESKTOP","colors":"grey"}],"file":false,"time":1514556835383,"location":{"filename":"expressLogger.js","line":43}},"args":{"0":"/api/user/auth"},"contextString":"\u001b[36m[Express]\u001b[39m\u001b[31m[::1]\u001b[39m\u001b[32m[POST]\u001b[39m\u001b[90m[DESKTOP]\u001b[39m 2017-12-29T14:13:55.383Z ","argsString":"/api/user/auth","message":"\u001b[36m[Express]\u001b[39m\u001b[31m[::1]\u001b[39m\u001b[32m[POST]\u001b[39m\u001b[90m[DESKTOP]\u001b[39m 2017-12-29T14:13:55.383Z /api/user/auth"}
{"type":"info","show":{"tags":true,"location":false,"time":true,"date":false},"context":{"tags":[{"msg":"Express","colors":"cyan"},{"msg":"::1","colors":"red"},{"msg":"POST","colors":"green"},{"msg":"DESKTOP","colors":"grey"}],"file":false,"time":1514556894542,"location":{"filename":"expressLogger.js","line":43}},"args":{"0":"/api/user/auth"},"contextString":"\u001b[36m[Express]\u001b[39m\u001b[31m[::1]\u001b[39m\u001b[32m[POST]\u001b[39m\u001b[90m[DESKTOP]\u001b[39m 2017-12-29T14:14:54.542Z ","argsString":"/api/user/auth","message":"\u001b[36m[Express]\u001b[39m\u001b[31m[::1]\u001b[39m\u001b[32m[POST]\u001b[39m\u001b[90m[DESKTOP]\u001b[39m 2017-12-29T14:14:54.542Z /api/user/auth"}
{"type":"info","show":{"tags":true,"location":false,"time":true,"date":false},"context":{"tags":[{"msg":"Express","colors":"cyan"},{"msg":"::1","colors":"red"},{"msg":"POST","colors":"green"},{"msg":"DESKTOP","colors":"grey"}],"file":false,"time":1514556903561,"location":{"filename":"expressLogger.js","line":43}},"args":{"0":"/api/user/auth"},"contextString":"\u001b[36m[Express]\u001b[39m\u001b[31m[::1]\u001b[39m\u001b[32m[POST]\u001b[39m\u001b[90m[DESKTOP]\u001b[39m 2017-12-29T14:15:03.561Z ","argsString":"/api/user/auth","message":"\u001b[36m[Express]\u001b[39m\u001b[31m[::1]\u001b[39m\u001b[32m[POST]\u001b[39m\u001b[90m[DESKTOP]\u001b[39m 2017-12-29T14:15:03.561Z /api/user/auth"}
{"type":"info","show":{"tags":true,"location":false,"time":true,"date":false},"context":{"tags":[{"msg":"Express","colors":"cyan"},{"msg":"::1","colors":"red"},{"msg":"POST","colors":"green"},{"msg":"DESKTOP","colors":"grey"}],"file":false,"time":1514556905711,"location":{"filename":"expressLogger.js","line":43}},"args":{"0":"/api/user/auth"},"contextString":"\u001b[36m[Express]\u001b[39m\u001b[31m[::1]\u001b[39m\u001b[32m[POST]\u001b[39m\u001b[90m[DESKTOP]\u001b[39m 2017-12-29T14:15:05.711Z ","argsString":"/api/user/auth","message":"\u001b[36m[Express]\u001b[39m\u001b[31m[::1]\u001b[39m\u001b[32m[POST]\u001b[39m\u001b[90m[DESKTOP]\u001b[39m 2017-12-29T14:15:05.711Z /api/user/auth"}
{"type":"info","show":{"tags":true,"location":false,"time":true,"date":false},"context":{"tags":[{"msg":"Express","colors":"cyan"},{"msg":"::1","colors":"red"},{"msg":"POST","colors":"green"},{"msg":"DESKTOP","colors":"grey"}],"file":false,"time":1514556905716,"location":{"filename":"expressLogger.js","line":43}},"args":{"0":"/api/user/logout"},"contextString":"\u001b[36m[Express]\u001b[39m\u001b[31m[::1]\u001b[39m\u001b[32m[POST]\u001b[39m\u001b[90m[DESKTOP]\u001b[39m 2017-12-29T14:15:05.716Z ","argsString":"/api/user/logout","message":"\u001b[36m[Express]\u001b[39m\u001b[31m[::1]\u001b[39m\u001b[32m[POST]\u001b[39m\u001b[90m[DESKTOP]\u001b[39m 2017-12-29T14:15:05.716Z /api/user/logout"}
{"type":"info","show":{"tags":true,"location":false,"time":true,"date":false},"context":{"tags":[{"msg":"Express","colors":"cyan"},{"msg":"::1","colors":"red"},{"msg":"POST","colors":"green"},{"msg":"DESKTOP","colors":"grey"}],"file":false,"time":1514557689314,"location":{"filename":"expressLogger.js","line":43}},"args":{"0":"/api/user/auth"},"contextString":"\u001b[36m[Express]\u001b[39m\u001b[31m[::1]\u001b[39m\u001b[32m[POST]\u001b[39m\u001b[90m[DESKTOP]\u001b[39m 2017-12-29T14:28:09.314Z ","argsString":"/api/user/auth","message":"\u001b[36m[Express]\u001b[39m\u001b[31m[::1]\u001b[39m\u001b[32m[POST]\u001b[39m\u001b[90m[DESKTOP]\u001b[39m 2017-12-29T14:28:09.314Z /api/user/auth"}
{"type":"info","show":{"tags":true,"location":false,"time":true,"date":false},"context":{"tags":[{"msg":"Express","colors":"cyan"},{"msg":"::1","colors":"red"},{"msg":"POST","colors":"green"},{"msg":"DESKTOP","colors":"grey"}],"file":false,"time":1514557709695,"location":{"filename":"expressLogger.js","line":43}},"args":{"0":"/api/user/auth"},"contextString":"\u001b[36m[Express]\u001b[39m\u001b[31m[::1]\u001b[39m\u001b[32m[POST]\u001b[39m\u001b[90m[DESKTOP]\u001b[39m 2017-12-29T14:28:29.695Z ","argsString":"/api/user/auth","message":"\u001b[36m[Express]\u001b[39m\u001b[31m[::1]\u001b[39m\u001b[32m[POST]\u001b[39m\u001b[90m[DESKTOP]\u001b[39m 2017-12-29T14:28:29.695Z /api/user/auth"}
{"type":"info","show":{"tags":true,"location":false,"time":true,"date":false},"context":{"tags":[{"msg":"Express","colors":"cyan"},{"msg":"::1","colors":"red"},{"msg":"POST","colors":"green"},{"msg":"DESKTOP","colors":"grey"}],"file":false,"time":1514557715843,"location":{"filename":"expressLogger.js","line":43}},"args":{"0":"/api/user/auth"},"contextString":"\u001b[36m[Express]\u001b[39m\u001b[31m[::1]\u001b[39m\u001b[32m[POST]\u001b[39m\u001b[90m[DESKTOP]\u001b[39m 2017-12-29T14:28:35.843Z ","argsString":"/api/user/auth","message":"\u001b[36m[Express]\u001b[39m\u001b[31m[::1]\u001b[39m\u001b[32m[POST]\u001b[39m\u001b[90m[DESKTOP]\u001b[39m 2017-12-29T14:28:35.843Z /api/user/auth"}
{"type":"info","show":{"tags":true,"location":false,"time":true,"date":false},"context":{"tags":[{"msg":"Express","colors":"cyan"},{"msg":"::1","colors":"red"},{"msg":"POST","colors":"green"},{"msg":"DESKTOP","colors":"grey"}],"file":false,"time":1514557788850,"location":{"filename":"expressLogger.js","line":43}},"args":{"0":"/api/user/auth"},"contextString":"\u001b[36m[Express]\u001b[39m\u001b[31m[::1]\u001b[39m\u001b[32m[POST]\u001b[39m\u001b[90m[DESKTOP]\u001b[39m 2017-12-29T14:29:48.850Z ","argsString":"/api/user/auth","message":"\u001b[36m[Express]\u001b[39m\u001b[31m[::1]\u001b[39m\u001b[32m[POST]\u001b[39m\u001b[90m[DESKTOP]\u001b[39m 2017-12-29T14:29:48.850Z /api/user/auth"}
{"type":"info","show":{"tags":true,"location":false,"time":true,"date":false},"context":{"tags":[{"msg":"Express","colors":"cyan"},{"msg":"::1","colors":"red"},{"msg":"POST","colors":"green"},{"msg":"DESKTOP","colors":"grey"}],"file":false,"time":1514557815251,"location":{"filename":"expressLogger.js","line":43}},"args":{"0":"/api/user/auth"},"contextString":"\u001b[36m[Express]\u001b[39m\u001b[31m[::1]\u001b[39m\u001b[32m[POST]\u001b[39m\u001b[90m[DESKTOP]\u001b[39m 2017-12-29T14:30:15.251Z ","argsString":"/api/user/auth","message":"\u001b[36m[Express]\u001b[39m\u001b[31m[::1]\u001b[39m\u001b[32m[POST]\u001b[39m\u001b[90m[DESKTOP]\u001b[39m 2017-12-29T14:30:15.251Z /api/user/auth"}
{"type":"info","show":{"tags":true,"location":false,"time":true,"date":false},"context":{"tags":[{"msg":"Express","colors":"cyan"},{"msg":"::1","colors":"red"},{"msg":"POST","colors":"green"},{"msg":"DESKTOP","colors":"grey"}],"file":false,"time":1514557823357,"location":{"filename":"expressLogger.js","line":43}},"args":{"0":"/api/user/auth"},"contextString":"\u001b[36m[Express]\u001b[39m\u001b[31m[::1]\u001b[39m\u001b[32m[POST]\u001b[39m\u001b[90m[DESKTOP]\u001b[39m 2017-12-29T14:30:23.357Z ","argsString":"/api/user/auth","message":"\u001b[36m[Express]\u001b[39m\u001b[31m[::1]\u001b[39m\u001b[32m[POST]\u001b[39m\u001b[90m[DESKTOP]\u001b[39m 2017-12-29T14:30:23.357Z /api/user/auth"}
{"type":"info","show":{"tags":true,"location":false,"time":true,"date":false},"context":{"tags":[{"msg":"Express","colors":"cyan"},{"msg":"::1","colors":"red"},{"msg":"POST","colors":"green"},{"msg":"DESKTOP","colors":"grey"}],"file":false,"time":1514557862180,"location":{"filename":"expressLogger.js","line":43}},"args":{"0":"/api/user/auth"},"contextString":"\u001b[36m[Express]\u001b[39m\u001b[31m[::1]\u001b[39m\u001b[32m[POST]\u001b[39m\u001b[90m[DESKTOP]\u001b[39m 2017-12-29T14:31:02.180Z ","argsString":"/api/user/auth","message":"\u001b[36m[Express]\u001b[39m\u001b[31m[::1]\u001b[39m\u001b[32m[POST]\u001b[39m\u001b[90m[DESKTOP]\u001b[39m 2017-12-29T14:31:02.180Z /api/user/auth"}
{"type":"info","show":{"tags":true,"location":false,"time":true,"date":false},"context":{"tags":[{"msg":"Express","colors":"cyan"},{"msg":"::1","colors":"red"},{"msg":"POST","colors":"green"},{"msg":"DESKTOP","colors":"grey"}],"file":false,"time":1514557884953,"location":{"filename":"expressLogger.js","line":43}},"args":{"0":"/api/user/auth"},"contextString":"\u001b[36m[Express]\u001b[39m\u001b[31m[::1]\u001b[39m\u001b[32m[POST]\u001b[39m\u001b[90m[DESKTOP]\u001b[39m 2017-12-29T14:31:24.953Z ","argsString":"/api/user/auth","message":"\u001b[36m[Express]\u001b[39m\u001b[31m[::1]\u001b[39m\u001b[32m[POST]\u001b[39m\u001b[90m[DESKTOP]\u001b[39m 2017-12-29T14:31:24.953Z /api/user/auth"}
{"type":"info","show":{"tags":true,"location":false,"time":true,"date":false},"context":{"tags":[{"msg":"Express","colors":"cyan"},{"msg":"::1","colors":"red"},{"msg":"POST","colors":"green"},{"msg":"DESKTOP","colors":"grey"}],"file":false,"time":1514557884960,"location":{"filename":"expressLogger.js","line":43}},"args":{"0":"/api/user/logout"},"contextString":"\u001b[36m[Express]\u001b[39m\u001b[31m[::1]\u001b[39m\u001b[32m[POST]\u001b[39m\u001b[90m[DESKTOP]\u001b[39m 2017-12-29T14:31:24.960Z ","argsString":"/api/user/logout","message":"\u001b[36m[Express]\u001b[39m\u001b[31m[::1]\u001b[39m\u001b[32m[POST]\u001b[39m\u001b[90m[DESKTOP]\u001b[39m 2017-12-29T14:31:24.960Z /api/user/logout"}
{"type":"info","show":{"tags":true,"location":false,"time":true,"date":false},"context":{"tags":[{"msg":"Express","colors":"cyan"},{"msg":"::1","colors":"red"},{"msg":"POST","colors":"green"},{"msg":"DESKTOP","colors":"grey"}],"file":false,"time":1514557887341,"location":{"filename":"expressLogger.js","line":43}},"args":{"0":"/api/user/auth"},"contextString":"\u001b[36m[Express]\u001b[39m\u001b[31m[::1]\u001b[39m\u001b[32m[POST]\u001b[39m\u001b[90m[DESKTOP]\u001b[39m 2017-12-29T14:31:27.341Z ","argsString":"/api/user/auth","message":"\u001b[36m[Express]\u001b[39m\u001b[31m[::1]\u001b[39m\u001b[32m[POST]\u001b[39m\u001b[90m[DESKTOP]\u001b[39m 2017-12-29T14:31:27.341Z /api/user/auth"}
{"type":"info","show":{"tags":true,"location":false,"time":true,"date":false},"context":{"tags":[{"msg":"Express","colors":"cyan"},{"msg":"::1","colors":"red"},{"msg":"POST","colors":"green"},{"msg":"DESKTOP","colors":"grey"}],"file":false,"time":1514557892643,"location":{"filename":"expressLogger.js","line":43}},"args":{"0":"/api/user/auth"},"contextString":"\u001b[36m[Express]\u001b[39m\u001b[31m[::1]\u001b[39m\u001b[32m[POST]\u001b[39m\u001b[90m[DESKTOP]\u001b[39m 2017-12-29T14:31:32.643Z ","argsString":"/api/user/auth","message":"\u001b[36m[Express]\u001b[39m\u001b[31m[::1]\u001b[39m\u001b[32m[POST]\u001b[39m\u001b[90m[DESKTOP]\u001b[39m 2017-12-29T14:31:32.643Z /api/user/auth"}
{"type":"info","show":{"tags":true,"location":false,"time":true,"date":false},"context":{"tags":[{"msg":"Express","colors":"cyan"},{"msg":"::1","colors":"red"},{"msg":"POST","colors":"green"},{"msg":"DESKTOP","colors":"grey"}],"file":false,"time":1514557939472,"location":{"filename":"expressLogger.js","line":43}},"args":{"0":"/api/user/auth"},"contextString":"\u001b[36m[Express]\u001b[39m\u001b[31m[::1]\u001b[39m\u001b[32m[POST]\u001b[39m\u001b[90m[DESKTOP]\u001b[39m 2017-12-29T14:32:19.472Z ","argsString":"/api/user/auth","message":"\u001b[36m[Express]\u001b[39m\u001b[31m[::1]\u001b[39m\u001b[32m[POST]\u001b[39m\u001b[90m[DESKTOP]\u001b[39m 2017-12-29T14:32:19.472Z /api/user/auth"}
{"type":"info","show":{"tags":true,"location":false,"time":true,"date":false},"context":{"tags":[{"msg":"Express","colors":"cyan"},{"msg":"::1","colors":"red"},{"msg":"POST","colors":"green"},{"msg":"DESKTOP","colors":"grey"}],"file":false,"time":1514557962503,"location":{"filename":"expressLogger.js","line":43}},"args":{"0":"/api/user/auth"},"contextString":"\u001b[36m[Express]\u001b[39m\u001b[31m[::1]\u001b[39m\u001b[32m[POST]\u001b[39m\u001b[90m[DESKTOP]\u001b[39m 2017-12-29T14:32:42.503Z ","argsString":"/api/user/auth","message":"\u001b[36m[Express]\u001b[39m\u001b[31m[::1]\u001b[39m\u001b[32m[POST]\u001b[39m\u001b[90m[DESKTOP]\u001b[39m 2017-12-29T14:32:42.503Z /api/user/auth"}
{"type":"info","show":{"tags":true,"location":false,"time":true,"date":false},"context":{"tags":[{"msg":"Express","colors":"cyan"},{"msg":"::1","colors":"red"},{"msg":"POST","colors":"green"},{"msg":"DESKTOP","colors":"grey"}],"file":false,"time":1514557969352,"location":{"filename":"expressLogger.js","line":43}},"args":{"0":"/api/user/auth"},"contextString":"\u001b[36m[Express]\u001b[39m\u001b[31m[::1]\u001b[39m\u001b[32m[POST]\u001b[39m\u001b[90m[DESKTOP]\u001b[39m 2017-12-29T14:32:49.352Z ","argsString":"/api/user/auth","message":"\u001b[36m[Express]\u001b[39m\u001b[31m[::1]\u001b[39m\u001b[32m[POST]\u001b[39m\u001b[90m[DESKTOP]\u001b[39m 2017-12-29T14:32:49.352Z /api/user/auth"}
{"type":"info","show":{"tags":true,"location":false,"time":true,"date":false},"context":{"tags":[{"msg":"Express","colors":"cyan"},{"msg":"::1","colors":"red"},{"msg":"POST","colors":"green"},{"msg":"DESKTOP","colors":"grey"}],"file":false,"time":1514557976703,"location":{"filename":"expressLogger.js","line":43}},"args":{"0":"/api/user/auth"},"contextString":"\u001b[36m[Express]\u001b[39m\u001b[31m[::1]\u001b[39m\u001b[32m[POST]\u001b[39m\u001b[90m[DESKTOP]\u001b[39m 2017-12-29T14:32:56.703Z ","argsString":"/api/user/auth","message":"\u001b[36m[Express]\u001b[39m\u001b[31m[::1]\u001b[39m\u001b[32m[POST]\u001b[39m\u001b[90m[DESKTOP]\u001b[39m 2017-12-29T14:32:56.703Z /api/user/auth"}
{"type":"info","show":{"tags":true,"location":false,"time":true,"date":false},"context":{"tags":[{"msg":"Express","colors":"cyan"},{"msg":"::1","colors":"red"},{"msg":"POST","colors":"green"},{"msg":"DESKTOP","colors":"grey"}],"file":false,"time":1514558035741,"location":{"filename":"expressLogger.js","line":43}},"args":{"0":"/api/user/auth"},"contextString":"\u001b[36m[Express]\u001b[39m\u001b[31m[::1]\u001b[39m\u001b[32m[POST]\u001b[39m\u001b[90m[DESKTOP]\u001b[39m 2017-12-29T14:33:55.741Z ","argsString":"/api/user/auth","message":"\u001b[36m[Express]\u001b[39m\u001b[31m[::1]\u001b[39m\u001b[32m[POST]\u001b[39m\u001b[90m[DESKTOP]\u001b[39m 2017-12-29T14:33:55.741Z /api/user/auth"}
{"type":"info","show":{"tags":true,"location":false,"time":true,"date":false},"context":{"tags":[{"msg":"Express","colors":"cyan"},{"msg":"::1","colors":"red"},{"msg":"POST","colors":"green"},{"msg":"DESKTOP","colors":"grey"}],"file":false,"time":1514558037283,"location":{"filename":"expressLogger.js","line":43}},"args":{"0":"/api/user/auth"},"contextString":"\u001b[36m[Express]\u001b[39m\u001b[31m[::1]\u001b[39m\u001b[32m[POST]\u001b[39m\u001b[90m[DESKTOP]\u001b[39m 2017-12-29T14:33:57.283Z ","argsString":"/api/user/auth","message":"\u001b[36m[Express]\u001b[39m\u001b[31m[::1]\u001b[39m\u001b[32m[POST]\u001b[39m\u001b[90m[DESKTOP]\u001b[39m 2017-12-29T14:33:57.283Z /api/user/auth"}
{"type":"info","show":{"tags":true,"location":false,"time":true,"date":false},"context":{"tags":[{"msg":"Express","colors":"cyan"},{"msg":"::1","colors":"red"},{"msg":"POST","colors":"green"},{"msg":"DESKTOP","colors":"grey"}],"file":false,"time":1514558037482,"location":{"filename":"expressLogger.js","line":43}},"args":{"0":"/api/user/auth"},"contextString":"\u001b[36m[Express]\u001b[39m\u001b[31m[::1]\u001b[39m\u001b[32m[POST]\u001b[39m\u001b[90m[DESKTOP]\u001b[39m 2017-12-29T14:33:57.482Z ","argsString":"/api/user/auth","message":"\u001b[36m[Express]\u001b[39m\u001b[31m[::1]\u001b[39m\u001b[32m[POST]\u001b[39m\u001b[90m[DESKTOP]\u001b[39m 2017-12-29T14:33:57.482Z /api/user/auth"}
{"type":"info","show":{"tags":true,"location":false,"time":true,"date":false},"context":{"tags":[{"msg":"Express","colors":"cyan"},{"msg":"::1","colors":"red"},{"msg":"POST","colors":"green"},{"msg":"DESKTOP","colors":"grey"}],"file":false,"time":1514558037670,"location":{"filename":"expressLogger.js","line":43}},"args":{"0":"/api/user/auth"},"contextString":"\u001b[36m[Express]\u001b[39m\u001b[31m[::1]\u001b[39m\u001b[32m[POST]\u001b[39m\u001b[90m[DESKTOP]\u001b[39m 2017-12-29T14:33:57.670Z ","argsString":"/api/user/auth","message":"\u001b[36m[Express]\u001b[39m\u001b[31m[::1]\u001b[39m\u001b[32m[POST]\u001b[39m\u001b[90m[DESKTOP]\u001b[39m 2017-12-29T14:33:57.670Z /api/user/auth"}
{"type":"info","show":{"tags":true,"location":false,"time":true,"date":false},"context":{"tags":[{"msg":"Express","colors":"cyan"},{"msg":"::1","colors":"red"},{"msg":"POST","colors":"green"},{"msg":"DESKTOP","colors":"grey"}],"file":false,"time":1514558037852,"location":{"filename":"expressLogger.js","line":43}},"args":{"0":"/api/user/auth"},"contextString":"\u001b[36m[Express]\u001b[39m\u001b[31m[::1]\u001b[39m\u001b[32m[POST]\u001b[39m\u001b[90m[DESKTOP]\u001b[39m 2017-12-29T14:33:57.852Z ","argsString":"/api/user/auth","message":"\u001b[36m[Express]\u001b[39m\u001b[31m[::1]\u001b[39m\u001b[32m[POST]\u001b[39m\u001b[90m[DESKTOP]\u001b[39m 2017-12-29T14:33:57.852Z /api/user/auth"}
{"type":"info","show":{"tags":true,"location":false,"time":true,"date":false},"context":{"tags":[{"msg":"Express","colors":"cyan"},{"msg":"::1","colors":"red"},{"msg":"POST","colors":"green"},{"msg":"DESKTOP","colors":"grey"}],"file":false,"time":1514558038017,"location":{"filename":"expressLogger.js","line":43}},"args":{"0":"/api/user/auth"},"contextString":"\u001b[36m[Express]\u001b[39m\u001b[31m[::1]\u001b[39m\u001b[32m[POST]\u001b[39m\u001b[90m[DESKTOP]\u001b[39m 2017-12-29T14:33:58.017Z ","argsString":"/api/user/auth","message":"\u001b[36m[Express]\u001b[39m\u001b[31m[::1]\u001b[39m\u001b[32m[POST]\u001b[39m\u001b[90m[DESKTOP]\u001b[39m 2017-12-29T14:33:58.017Z /api/user/auth"}
{"type":"info","show":{"tags":true,"location":false,"time":true,"date":false},"context":{"tags":[{"msg":"Express","colors":"cyan"},{"msg":"::1","colors":"red"},{"msg":"POST","colors":"green"},{"msg":"DESKTOP","colors":"grey"}],"file":false,"time":1514558051790,"location":{"filename":"expressLogger.js","line":43}},"args":{"0":"/api/user/auth"},"contextString":"\u001b[36m[Express]\u001b[39m\u001b[31m[::1]\u001b[39m\u001b[32m[POST]\u001b[39m\u001b[90m[DESKTOP]\u001b[39m 2017-12-29T14:34:11.790Z ","argsString":"/api/user/auth","message":"\u001b[36m[Express]\u001b[39m\u001b[31m[::1]\u001b[39m\u001b[32m[POST]\u001b[39m\u001b[90m[DESKTOP]\u001b[39m 2017-12-29T14:34:11.790Z /api/user/auth"}
{"type":"info","show":{"tags":true,"location":false,"time":true,"date":false},"context":{"tags":[{"msg":"Express","colors":"cyan"},{"msg":"::1","colors":"red"},{"msg":"POST","colors":"green"},{"msg":"DESKTOP","colors":"grey"}],"file":false,"time":1514558056652,"location":{"filename":"expressLogger.js","line":43}},"args":{"0":"/api/user/login"},"contextString":"\u001b[36m[Express]\u001b[39m\u001b[31m[::1]\u001b[39m\u001b[32m[POST]\u001b[39m\u001b[90m[DESKTOP]\u001b[39m 2017-12-29T14:34:16.652Z ","argsString":"/api/user/login","message":"\u001b[36m[Express]\u001b[39m\u001b[31m[::1]\u001b[39m\u001b[32m[POST]\u001b[39m\u001b[90m[DESKTOP]\u001b[39m 2017-12-29T14:34:16.652Z /api/user/login"}
{"type":"info","show":{"tags":true,"location":false,"time":true,"date":false},"context":{"tags":[{"msg":"Express","colors":"cyan"},{"msg":"::1","colors":"red"},{"msg":"POST","colors":"green"},{"msg":"DESKTOP","colors":"grey"}],"file":false,"time":1514558066510,"location":{"filename":"expressLogger.js","line":43}},"args":{"0":"/api/user/auth"},"contextString":"\u001b[36m[Express]\u001b[39m\u001b[31m[::1]\u001b[39m\u001b[32m[POST]\u001b[39m\u001b[90m[DESKTOP]\u001b[39m 2017-12-29T14:34:26.510Z ","argsString":"/api/user/auth","message":"\u001b[36m[Express]\u001b[39m\u001b[31m[::1]\u001b[39m\u001b[32m[POST]\u001b[39m\u001b[90m[DESKTOP]\u001b[39m 2017-12-29T14:34:26.510Z /api/user/auth"}
{"type":"info","show":{"tags":true,"location":false,"time":true,"date":false},"context":{"tags":[{"msg":"Express","colors":"cyan"},{"msg":"::1","colors":"red"},{"msg":"POST","colors":"green"},{"msg":"DESKTOP","colors":"grey"}],"file":false,"time":1514558071144,"location":{"filename":"expressLogger.js","line":43}},"args":{"0":"/api/user/auth"},"contextString":"\u001b[36m[Express]\u001b[39m\u001b[31m[::1]\u001b[39m\u001b[32m[POST]\u001b[39m\u001b[90m[DESKTOP]\u001b[39m 2017-12-29T14:34:31.144Z ","argsString":"/api/user/auth","message":"\u001b[36m[Express]\u001b[39m\u001b[31m[::1]\u001b[39m\u001b[32m[POST]\u001b[39m\u001b[90m[DESKTOP]\u001b[39m 2017-12-29T14:34:31.144Z /api/user/auth"}
{"type":"info","show":{"tags":true,"location":false,"time":true,"date":false},"context":{"tags":[{"msg":"Express","colors":"cyan"},{"msg":"::1","colors":"red"},{"msg":"POST","colors":"green"},{"msg":"DESKTOP","colors":"grey"}],"file":false,"time":1514558072092,"location":{"filename":"expressLogger.js","line":43}},"args":{"0":"/api/user/auth"},"contextString":"\u001b[36m[Express]\u001b[39m\u001b[31m[::1]\u001b[39m\u001b[32m[POST]\u001b[39m\u001b[90m[DESKTOP]\u001b[39m 2017-12-29T14:34:32.092Z ","argsString":"/api/user/auth","message":"\u001b[36m[Express]\u001b[39m\u001b[31m[::1]\u001b[39m\u001b[32m[POST]\u001b[39m\u001b[90m[DESKTOP]\u001b[39m 2017-12-29T14:34:32.092Z /api/user/auth"}
{"type":"info","show":{"tags":true,"location":false,"time":true,"date":false},"context":{"tags":[{"msg":"Express","colors":"cyan"},{"msg":"::1","colors":"red"},{"msg":"POST","colors":"green"},{"msg":"DESKTOP","colors":"grey"}],"file":false,"time":1514558085205,"location":{"filename":"expressLogger.js","line":43}},"args":{"0":"/api/user/auth"},"contextString":"\u001b[36m[Express]\u001b[39m\u001b[31m[::1]\u001b[39m\u001b[32m[POST]\u001b[39m\u001b[90m[DESKTOP]\u001b[39m 2017-12-29T14:34:45.205Z ","argsString":"/api/user/auth","message":"\u001b[36m[Express]\u001b[39m\u001b[31m[::1]\u001b[39m\u001b[32m[POST]\u001b[39m\u001b[90m[DESKTOP]\u001b[39m 2017-12-29T14:34:45.205Z /api/user/auth"}
{"type":"info","show":{"tags":true,"location":false,"time":true,"date":false},"context":{"tags":[{"msg":"Express","colors":"cyan"},{"msg":"::1","colors":"red"},{"msg":"POST","colors":"green"},{"msg":"DESKTOP","colors":"grey"}],"file":false,"time":1514558085235,"location":{"filename":"expressLogger.js","line":43}},"args":{"0":"/api/user/logout"},"contextString":"\u001b[36m[Express]\u001b[39m\u001b[31m[::1]\u001b[39m\u001b[32m[POST]\u001b[39m\u001b[90m[DESKTOP]\u001b[39m 2017-12-29T14:34:45.235Z ","argsString":"/api/user/logout","message":"\u001b[36m[Express]\u001b[39m\u001b[31m[::1]\u001b[39m\u001b[32m[POST]\u001b[39m\u001b[90m[DESKTOP]\u001b[39m 2017-12-29T14:34:45.235Z /api/user/logout"}
{"type":"info","show":{"tags":true,"location":false,"time":true,"date":false},"context":{"tags":[{"msg":"Express","colors":"cyan"},{"msg":"::1","colors":"red"},{"msg":"POST","colors":"green"},{"msg":"DESKTOP","colors":"grey"}],"file":false,"time":1514558088335,"location":{"filename":"expressLogger.js","line":43}},"args":{"0":"/api/user/login"},"contextString":"\u001b[36m[Express]\u001b[39m\u001b[31m[::1]\u001b[39m\u001b[32m[POST]\u001b[39m\u001b[90m[DESKTOP]\u001b[39m 2017-12-29T14:34:48.335Z ","argsString":"/api/user/login","message":"\u001b[36m[Express]\u001b[39m\u001b[31m[::1]\u001b[39m\u001b[32m[POST]\u001b[39m\u001b[90m[DESKTOP]\u001b[39m 2017-12-29T14:34:48.335Z /api/user/login"}
{"type":"info","show":{"tags":true,"location":false,"time":true,"date":false},"context":{"tags":[{"msg":"Express","colors":"cyan"},{"msg":"::1","colors":"red"},{"msg":"POST","colors":"green"},{"msg":"DESKTOP","colors":"grey"}],"file":false,"time":1514558090253,"location":{"filename":"expressLogger.js","line":43}},"args":{"0":"/api/user/auth"},"contextString":"\u001b[36m[Express]\u001b[39m\u001b[31m[::1]\u001b[39m\u001b[32m[POST]\u001b[39m\u001b[90m[DESKTOP]\u001b[39m 2017-12-29T14:34:50.253Z ","argsString":"/api/user/auth","message":"\u001b[36m[Express]\u001b[39m\u001b[31m[::1]\u001b[39m\u001b[32m[POST]\u001b[39m\u001b[90m[DESKTOP]\u001b[39m 2017-12-29T14:34:50.253Z /api/user/auth"}
{"type":"info","show":{"tags":true,"location":false,"time":true,"date":false},"context":{"tags":[{"msg":"Express","colors":"cyan"},{"msg":"::1","colors":"red"},{"msg":"POST","colors":"green"},{"msg":"DESKTOP","colors":"grey"}],"file":false,"time":1514558090257,"location":{"filename":"expressLogger.js","line":43}},"args":{"0":"/api/user/logout"},"contextString":"\u001b[36m[Express]\u001b[39m\u001b[31m[::1]\u001b[39m\u001b[32m[POST]\u001b[39m\u001b[90m[DESKTOP]\u001b[39m 2017-12-29T14:34:50.257Z ","argsString":"/api/user/logout","message":"\u001b[36m[Express]\u001b[39m\u001b[31m[::1]\u001b[39m\u001b[32m[POST]\u001b[39m\u001b[90m[DESKTOP]\u001b[39m 2017-12-29T14:34:50.257Z /api/user/logout"}
{"type":"info","show":{"tags":true,"location":false,"time":true,"date":false},"context":{"tags":[{"msg":"Express","colors":"cyan"},{"msg":"::1","colors":"red"},{"msg":"POST","colors":"green"},{"msg":"DESKTOP","colors":"grey"}],"file":false,"time":1514558091851,"location":{"filename":"expressLogger.js","line":43}},"args":{"0":"/api/user/login"},"contextString":"\u001b[36m[Express]\u001b[39m\u001b[31m[::1]\u001b[39m\u001b[32m[POST]\u001b[39m\u001b[90m[DESKTOP]\u001b[39m 2017-12-29T14:34:51.851Z ","argsString":"/api/user/login","message":"\u001b[36m[Express]\u001b[39m\u001b[31m[::1]\u001b[39m\u001b[32m[POST]\u001b[39m\u001b[90m[DESKTOP]\u001b[39m 2017-12-29T14:34:51.851Z /api/user/login"}
{"type":"info","show":{"tags":true,"location":false,"time":true,"date":false},"context":{"tags":[{"msg":"Express","colors":"cyan"},{"msg":"::1","colors":"red"},{"msg":"POST","colors":"green"},{"msg":"DESKTOP","colors":"grey"}],"file":false,"time":1514558093926,"location":{"filename":"expressLogger.js","line":43}},"args":{"0":"/api/user/auth"},"contextString":"\u001b[36m[Express]\u001b[39m\u001b[31m[::1]\u001b[39m\u001b[32m[POST]\u001b[39m\u001b[90m[DESKTOP]\u001b[39m 2017-12-29T14:34:53.926Z ","argsString":"/api/user/auth","message":"\u001b[36m[Express]\u001b[39m\u001b[31m[::1]\u001b[39m\u001b[32m[POST]\u001b[39m\u001b[90m[DESKTOP]\u001b[39m 2017-12-29T14:34:53.926Z /api/user/auth"}
{"type":"info","show":{"tags":true,"location":false,"time":true,"date":false},"context":{"tags":[{"msg":"Express","colors":"cyan"},{"msg":"::1","colors":"red"},{"msg":"POST","colors":"green"},{"msg":"DESKTOP","colors":"grey"}],"file":false,"time":1514558217774,"location":{"filename":"expressLogger.js","line":43}},"args":{"0":"/api/user/login"},"contextString":"\u001b[36m[Express]\u001b[39m\u001b[31m[::1]\u001b[39m\u001b[32m[POST]\u001b[39m\u001b[90m[DESKTOP]\u001b[39m 2017-12-29T14:36:57.774Z ","argsString":"/api/user/login","message":"\u001b[36m[Express]\u001b[39m\u001b[31m[::1]\u001b[39m\u001b[32m[POST]\u001b[39m\u001b[90m[DESKTOP]\u001b[39m 2017-12-29T14:36:57.774Z /api/user/login"}
{"type":"info","show":{"tags":true,"location":false,"time":true,"date":false},"context":{"tags":[{"msg":"Express","colors":"cyan"},{"msg":"::1","colors":"red"},{"msg":"POST","colors":"green"},{"msg":"DESKTOP","colors":"grey"}],"file":false,"time":1514558226538,"location":{"filename":"expressLogger.js","line":43}},"args":{"0":"/api/user/auth"},"contextString":"\u001b[36m[Express]\u001b[39m\u001b[31m[::1]\u001b[39m\u001b[32m[POST]\u001b[39m\u001b[90m[DESKTOP]\u001b[39m 2017-12-29T14:37:06.538Z ","argsString":"/api/user/auth","message":"\u001b[36m[Express]\u001b[39m\u001b[31m[::1]\u001b[39m\u001b[32m[POST]\u001b[39m\u001b[90m[DESKTOP]\u001b[39m 2017-12-29T14:37:06.538Z /api/user/auth"}
{"type":"info","show":{"tags":true,"location":false,"time":true,"date":false},"context":{"tags":[{"msg":"Express","colors":"cyan"},{"msg":"::1","colors":"red"},{"msg":"POST","colors":"green"},{"msg":"DESKTOP","colors":"grey"}],"file":false,"time":1514558234341,"location":{"filename":"expressLogger.js","line":43}},"args":{"0":"/api/user/login"},"contextString":"\u001b[36m[Express]\u001b[39m\u001b[31m[::1]\u001b[39m\u001b[32m[POST]\u001b[39m\u001b[90m[DESKTOP]\u001b[39m 2017-12-29T14:37:14.341Z ","argsString":"/api/user/login","message":"\u001b[36m[Express]\u001b[39m\u001b[31m[::1]\u001b[39m\u001b[32m[POST]\u001b[39m\u001b[90m[DESKTOP]\u001b[39m 2017-12-29T14:37:14.341Z /api/user/login"}
{"type":"info","show":{"tags":true,"location":false,"time":true,"date":false},"context":{"tags":[{"msg":"Express","colors":"cyan"},{"msg":"::1","colors":"red"},{"msg":"POST","colors":"green"},{"msg":"DESKTOP","colors":"grey"}],"file":false,"time":1514558314431,"location":{"filename":"expressLogger.js","line":43}},"args":{"0":"/api/user/auth"},"contextString":"\u001b[36m[Express]\u001b[39m\u001b[31m[::1]\u001b[39m\u001b[32m[POST]\u001b[39m\u001b[90m[DESKTOP]\u001b[39m 2017-12-29T14:38:34.431Z ","argsString":"/api/user/auth","message":"\u001b[36m[Express]\u001b[39m\u001b[31m[::1]\u001b[39m\u001b[32m[POST]\u001b[39m\u001b[90m[DESKTOP]\u001b[39m 2017-12-29T14:38:34.431Z /api/user/auth"}
{"type":"info","show":{"tags":true,"location":false,"time":true,"date":false},"context":{"tags":[{"msg":"Express","colors":"cyan"},{"msg":"::1","colors":"red"},{"msg":"POST","colors":"green"},{"msg":"DESKTOP","colors":"grey"}],"file":false,"time":1514558336525,"location":{"filename":"expressLogger.js","line":43}},"args":{"0":"/api/user/auth"},"contextString":"\u001b[36m[Express]\u001b[39m\u001b[31m[::1]\u001b[39m\u001b[32m[POST]\u001b[39m\u001b[90m[DESKTOP]\u001b[39m 2017-12-29T14:38:56.525Z ","argsString":"/api/user/auth","message":"\u001b[36m[Express]\u001b[39m\u001b[31m[::1]\u001b[39m\u001b[32m[POST]\u001b[39m\u001b[90m[DESKTOP]\u001b[39m 2017-12-29T14:38:56.525Z /api/user/auth"}
{"type":"info","show":{"tags":true,"location":false,"time":true,"date":false},"context":{"tags":[{"msg":"Express","colors":"cyan"},{"msg":"::1","colors":"red"},{"msg":"POST","colors":"green"},{"msg":"DESKTOP","colors":"grey"}],"file":false,"time":1514558444994,"location":{"filename":"expressLogger.js","line":43}},"args":{"0":"/api/user/login"},"contextString":"\u001b[36m[Express]\u001b[39m\u001b[31m[::1]\u001b[39m\u001b[32m[POST]\u001b[39m\u001b[90m[DESKTOP]\u001b[39m 2017-12-29T14:40:44.994Z ","argsString":"/api/user/login","message":"\u001b[36m[Express]\u001b[39m\u001b[31m[::1]\u001b[39m\u001b[32m[POST]\u001b[39m\u001b[90m[DESKTOP]\u001b[39m 2017-12-29T14:40:44.994Z /api/user/login"}
{"type":"info","show":{"tags":true,"location":false,"time":true,"date":false},"context":{"tags":[{"msg":"Express","colors":"cyan"},{"msg":"::1","colors":"red"},{"msg":"POST","colors":"green"},{"msg":"DESKTOP","colors":"grey"}],"file":false,"time":1514558944054,"location":{"filename":"expressLogger.js","line":43}},"args":{"0":"/api/user/auth"},"contextString":"\u001b[36m[Express]\u001b[39m\u001b[31m[::1]\u001b[39m\u001b[32m[POST]\u001b[39m\u001b[90m[DESKTOP]\u001b[39m 2017-12-29T14:49:04.054Z ","argsString":"/api/user/auth","message":"\u001b[36m[Express]\u001b[39m\u001b[31m[::1]\u001b[39m\u001b[32m[POST]\u001b[39m\u001b[90m[DESKTOP]\u001b[39m 2017-12-29T14:49:04.054Z /api/user/auth"}
